prefect_mcp_server_pkg/__init__.py
prefect_mcp_server_pkg/server.py
mseep_prefect_mcp_server-1.1.6.dist-info/METADATA
mseep_prefect_mcp_server-1.1.6.dist-info/WHEEL
mseep_prefect_mcp_server-1.1.6.dist-info/entry_points.txt
mseep_prefect_mcp_server-1.1.6.dist-info/RECORD
